{
  "id": "PL-208",
  "title": "Primary Diagonal Reflection Task",
  "description": "Reflect the grid across the primary diagonal (top-left to bottom-right)",
  "category": "🚀 Pre-Launch Ops",
  "difficulty": "Intermediate",
  "gridSize": 3,
  "timeLimit": null,
  "basePoints": 100,
  "requiredRankLevel": 1,
  "emojiSet": "celestial_set1",
  "examples": [
    {
      "input": [
        [
          8,
          5,
          8
        ],
        [
          9,
          2,
          0
        ],
        [
          4,
          5,
          2
        ]
      ],
      "output": [
        [
          2,
          2,
          7
        ],
        [
          7,
          4,
          2
        ],
        [
          6,
          1,
          9
        ]
      ]
    },
    {
      "input": [
        [
          2,
          7,
          2
        ],
        [
          5,
          0,
          7
        ],
        [
          7,
          1,
          6
        ]
      ],
      "output": [
        [
          2,
          1,
          8
        ],
        [
          9,
          8,
          3
        ],
        [
          5,
          8,
          2
        ]
      ]
    }
  ],
  "testInput": [
    [
      1,
      7,
      2
    ],
    [
      6,
      3,
      8
    ],
    [
      2,
      1,
      5
    ]
  ],
  "testOutput": [
    [
      1,
      6,
      2
    ],
    [
      7,
      3,
      1
    ],
    [
      2,
      8,
      5
    ]
  ],
  "hints": [
    "Imagine a line going from the top-left corner to the bottom-right corner of the grid ↘️. Flip the grid over this line.",
    "This is like swapping rows and columns - the first row becomes the first column, the second row becomes the second column, and so on.",
    "The number in the top-right corner will move to the bottom-left corner, like looking at the grid in a mirror along the diagonal."
  ],
  "transformationType": "primary_diagonal_reflection",
  "generated": true
}